approw/__init__.py
approw/v2/__init__.py
approw/v2/exceptions.py
approw/v2/authentication/__init__.py
approw/v2/authentication/approw.py
approw/v2/authentication/types.py
approw/v2/common/__init__.py
approw/v2/common/codegen.py
approw/v2/common/graphql.py
approw/v2/common/rest.py
approw/v2/common/utils.py
approw/v2/management/__init__.py
approw/v2/management/acl.py
approw/v2/management/applications.py
approw/v2/management/approw.py
approw/v2/management/authing.py
approw/v2/management/check_type.py
approw/v2/management/groups.py
approw/v2/management/policies.py
approw/v2/management/roles.py
approw/v2/management/token_provider.py
approw/v2/management/types.py
approw/v2/management/udf.py
approw/v2/management/users.py
approw/v2/test/__init__.py
approw/v2/test/authentication/__init__.py
approw/v2/test/authentication/test_authentication.py
approw/v2/test/utils/__init__.py
approw_py_sdk-1.0.8.dist-info/METADATA
approw_py_sdk-1.0.8.dist-info/WHEEL
approw_py_sdk-1.0.8.dist-info/top_level.txt
approw_py_sdk-1.0.8.dist-info/RECORD
