Metadata-Version: 2.1
Name: approw-py-sdk
Version: 1.0.8
Summary: Approw SDK for Python
Home-page: https://github.com/approw/approw-py-sdk
Author: approw
Author-email: info@approw.com
Maintainer: approw
Maintainer-email: info@approw.com
License: UNKNOWN
Keywords: approw sso AaaS IdaaS
Platform: UNKNOWN
Classifier: Programming Language :: Python :: 2
Classifier: Programming Language :: Python :: 2.7
Classifier: Programming Language :: Python :: 3
Classifier: Programming Language :: Python :: 3.2
Classifier: Programming Language :: Python :: 3.3
Classifier: Programming Language :: Python :: 3.4
Classifier: Programming Language :: Python :: 3.5
Classifier: Programming Language :: Python :: 3.6
Classifier: Programming Language :: Python :: 3.7
Requires-Dist: gql (==2.0.0)
Requires-Dist: graphql-core (<3,>=2.3.2)
Requires-Dist: requests
Requires-Dist: python-dateutil
Requires-Dist: rsa (==4.0)
